src/__init__.py
src/general.py
corehelper-0.0.1.dist-info/METADATA
corehelper-0.0.1.dist-info/WHEEL
corehelper-0.0.1.dist-info/top_level.txt
corehelper-0.0.1.dist-info/RECORD
