Metadata-Version: 2.1
Name: corehelper
Version: 0.0.1
Summary: Core useful utilities
Home-page: https://github.com/mrebolledo/core_helper.git
Author: Maximiliano Rebolledo
Author-email: Maximiliano Rebolledo <maxi.rebolledo@gmail.com>
Project-URL: Homepage, https://github.com/mrebolledo/core_helper.git
Classifier: Programming Language :: Python :: 3
Classifier: License :: OSI Approved :: MIT License
Classifier: Operating System :: OS Independent
Requires-Python: >=3.7
